{
    "cardTitle": "Super Energy Removal",
    "mainPokemon": "Super Energy Removal",
    "version": 1,
    "trainerInfo": {
        "item": true,
        "trainerOwned": false,
        "soleTrainer": false,
        "trainer": "Super Energy Removal"
    },
    "hasReverseHolo": false,
    "mainEnergy": "trainer",
    "illustrator": "Keiji Kinebuchi",
    "masterSetData": {
        "setName": "Base",
        "cardNumber": "79"
    },
    "release": {
        "releaseYear": 1999,
        "releaseMonth": 1,
        "releaseDay": 9
    },
    "tags": []
}